MANIFEST.in
README.md
setup.py
energympc/__init__.py
energympc.egg-info/PKG-INFO
energympc.egg-info/SOURCES.txt
energympc.egg-info/dependency_links.txt
energympc.egg-info/requires.txt
energympc.egg-info/top_level.txt
energympc/Cbc-refactor-win64-msvc14-mt/bin/cbc.exe
energympc/Cbc-refactor-win64-msvc14-mt/bin/clp.exe
energympc/Cbc-refactor-win64-msvc14-mt/include/coin-or/CbcBranchActual.hpp
energympc/Cbc-refactor-win64-msvc14-mt/include/coin-or/CbcBranchAllDifferent.hpp
energympc/Cbc-refactor-win64-msvc14-mt/include/coin-or/CbcBranchBase.hpp
energympc/Cbc-refactor-win64-msvc14-mt/include/coin-or/CbcBranchCut.hpp
energympc/Cbc-refactor-win64-msvc14-mt/include/coin-or/CbcBranchDecision.hpp
energympc/Cbc-refactor-win64-msvc14-mt/include/coin-or/CbcBranchDefaultDecision.hpp
energympc/Cbc-refactor-win64-msvc14-mt/include/coin-or/CbcBranchDynamic.hpp
energympc/Cbc-refactor-win64-msvc14-mt/include/coin-or/CbcBranchLotsize.hpp
energympc/Cbc-refactor-win64-msvc14-mt/include/coin-or/CbcBranchToFixLots.hpp
energympc/Cbc-refactor-win64-msvc14-mt/include/coin-or/CbcBranchingObject.hpp
energympc/Cbc-refactor-win64-msvc14-mt/include/coin-or/CbcClique.hpp
energympc/Cbc-refactor-win64-msvc14-mt/include/coin-or/CbcCompare.hpp
energympc/Cbc-refactor-win64-msvc14-mt/include/coin-or/CbcCompareActual.hpp
energympc/Cbc-refactor-win64-msvc14-mt/include/coin-or/CbcCompareBase.hpp
energympc/Cbc-refactor-win64-msvc14-mt/include/coin-or/CbcCompareDefault.hpp
energympc/Cbc-refactor-win64-msvc14-mt/include/coin-or/CbcCompareDepth.hpp
energympc/Cbc-refactor-win64-msvc14-mt/include/coin-or/CbcCompareEstimate.hpp
energympc/Cbc-refactor-win64-msvc14-mt/include/coin-or/CbcCompareObjective.hpp
energympc/Cbc-refactor-win64-msvc14-mt/include/coin-or/CbcConfig.h
energympc/Cbc-refactor-win64-msvc14-mt/include/coin-or/CbcConsequence.hpp
energympc/Cbc-refactor-win64-msvc14-mt/include/coin-or/CbcCountRowCut.hpp
energympc/Cbc-refactor-win64-msvc14-mt/include/coin-or/CbcCutGenerator.hpp
energympc/Cbc-refactor-win64-msvc14-mt/include/coin-or/CbcCutModifier.hpp
energympc/Cbc-refactor-win64-msvc14-mt/include/coin-or/CbcCutSubsetModifier.hpp
