Metadata-Version: 2.1
Name: energympc
Version: 1.0.3
Home-page: 
Author: imby
Author-email: 
Classifier: Programming Language :: Python :: 3
Classifier: License :: OSI Approved :: MIT License
Classifier: Operating System :: OS Independent
Requires-Dist: pyomo
Requires-Dist: pandas
Requires-Dist: numpy
Requires-Dist: typing
Requires-Dist: matplotlib
